{
  "name": "Dark+ (VS Code)",
  "type": "dark",
  "colors": {
    "editor.background": "#1e1e1e",
    "editor.foreground": "#d4d4d4",
    "editorLineNumber.foreground": "#858585",
    "editorLineNumber.activeForeground": "#c6c6c6",
    "activityBar.background": "#333333",
    "activityBar.foreground": "#ffffff",
    "sideBar.background": "#252526",
    "sideBar.foreground": "#cccccc",
    "sideBarTitle.foreground": "#bbbbbb",
    "titleBar.activeBackground": "#3c3c3c",
    "titleBar.activeForeground": "#cccccc",
    "titleBar.inactiveBackground": "#3c3c3c",
    "titleBar.inactiveForeground": "#999999",
    "list.activeSelectionBackground": "#094771",
    "list.activeSelectionForeground": "#ffffff",
    "list.hoverBackground": "#2a2d2e",
    "list.inactiveSelectionBackground": "#37373d",
    "input.background": "#3c3c3c",
    "input.foreground": "#cccccc",
    "input.border": "#3c3c3c",
    "input.placeholderForeground": "#a6a6a6",
    "button.background": "#0e639c",
    "button.foreground": "#ffffff",
    "button.hoverBackground": "#1177bb",
    "statusBar.background": "#007acc",
    "statusBar.foreground": "#ffffff",
    "scrollbarSlider.background": "#79797966",
    "scrollbarSlider.hoverBackground": "#646464b3",
    "scrollbarSlider.activeBackground": "#bfbfbf66",
    "panel.background": "#1e1e1e",
    "panel.border": "#80808059",
    "focusBorder": "#007fd4",
    "foreground": "#cccccc",
    "descriptionForeground": "#ccccccb3",
    "errorForeground": "#f48771",
    "gitDecoration.addedResourceForeground": "#81b88b",
    "gitDecoration.modifiedResourceForeground": "#e2c08d",
    "gitDecoration.deletedResourceForeground": "#c74e39",
    "gitDecoration.untrackedResourceForeground": "#73c991"
  }
}
